pyfigure98/__init__.py
pyfigure98/Figure/__init__.py
pyfigure98/Figure/_place_holder.py
pyfigure98/Figure/_set_figure.py
pyfigure98/Figure/_template_handling.py
pyfigure98/Figure/Chart/__init__.py
pyfigure98/Figure/Chart/_axes_methods.py
pyfigure98/Figure/Chart/_chart_methods.py
pyfigure98/Figure/Chart/_place_holder.py
pyfigure98/Figure/Chart/_plot_methods.py
pyfigure98/Figure/Templates/default.json
pyfigure98-1.1.1.dist-info/LICENSE
pyfigure98-1.1.1.dist-info/METADATA
pyfigure98-1.1.1.dist-info/WHEEL
pyfigure98-1.1.1.dist-info/top_level.txt
pyfigure98-1.1.1.dist-info/RECORD
