Metadata-Version: 2.1
Name: pyfigure98
Version: 1.1.1
Summary: Package to make plots easily.
Author-email: Antoine Mouchamps <antoine.mouchamps@gmail.com>
Project-URL: Homepage, https://github.com/antoine-mouchamps/pyfigure98
Project-URL: Bug Tracker, https://github.com/antoine-mouchamps/pyfigure98/issues
Classifier: Programming Language :: Python :: 3
Classifier: License :: OSI Approved :: MIT License
Classifier: Operating System :: OS Independent
Requires-Python: >=3.7
License-File: LICENSE
